apple_notes_parser/__init__.py
apple_notes_parser/__main__.py
apple_notes_parser/cli.py
apple_notes_parser/database.py
apple_notes_parser/embedded_objects.py
apple_notes_parser/exceptions.py
apple_notes_parser/models.py
apple_notes_parser/notestore.proto
apple_notes_parser/notestore_pb2.py
apple_notes_parser/parser.py
apple_notes_parser/protobuf_parser.py
apple_notes_parser-0.2.0.dist-info/METADATA
apple_notes_parser-0.2.0.dist-info/WHEEL
apple_notes_parser-0.2.0.dist-info/entry_points.txt
apple_notes_parser-0.2.0.dist-info/RECORD
