Metadata-Version: 2.4
Name: apple-notes-parser
Version: 0.2.0
Summary: A Python library for reading and parsing Apple Notes SQLite databases with comprehensive CLI tools
Project-URL: Homepage, https://github.com/rhettbull/apple-notes-parser
Project-URL: Repository, https://github.com/rhettbull/apple-notes-parser
Project-URL: Documentation, https://github.com/rhettbull/apple-notes-parser#readme
Project-URL: Bug Reports, https://github.com/rhettbull/apple-notes-parser/issues
Project-URL: Source Code, https://github.com/rhettbull/apple-notes-parser
Author-email: Rhet Turnbull <rturnbull+git@gmail.com>
Maintainer-email: Rhet Turnbull <rturnbull+git@gmail.com>
License: MIT
Keywords: apple,cli,database,extraction,macos,notes,parser,protobuf,sqlite
Classifier: Development Status :: 4 - Beta
Classifier: Environment :: Console
Classifier: Intended Audience :: Developers
Classifier: Intended Audience :: End Users/Desktop
Classifier: License :: OSI Approved :: MIT License
Classifier: Operating System :: MacOS
Classifier: Operating System :: POSIX
Classifier: Operating System :: Unix
Classifier: Programming Language :: Python :: 3
Classifier: Programming Language :: Python :: 3 :: Only
Classifier: Programming Language :: Python :: 3.11
Classifier: Programming Language :: Python :: 3.12
Classifier: Programming Language :: Python :: 3.13
Classifier: Topic :: Database
Classifier: Topic :: Software Development :: Libraries :: Python Modules
Classifier: Topic :: System :: Archiving
Classifier: Topic :: Utilities
Requires-Python: >=3.11
Requires-Dist: protobuf>=6.31.1
Provides-Extra: dev
Requires-Dist: clirunner>=0.2.0; extra == 'dev'
Requires-Dist: grpcio-tools>=1.74.0; extra == 'dev'
Requires-Dist: mypy>=1.13.0; extra == 'dev'
Requires-Dist: pytest-cov>=4.0.0; extra == 'dev'
Requires-Dist: pytest>=8.0.0; extra == 'dev'
Requires-Dist: ruff>=0.8.0; extra == 'dev'
